{
    "resourceCache": [
        {
            "path": "project/null.js",
            "id": "project/null.js",
            "_requiredCSSMap": {},
            "_requiredModuleMap": {},
            "_requiredAsyncModuleMap": {},
            "_requiredTextToResolvedID": {},
            "type": "JS",
            "networkSize": 0,
            "isModule": false,
            "isNopackage": false,
            "isNonblocking": false,
            "requiredCSS": [],
            "requiredModules": [],
            "requiredAsyncModules": [],
            "mtime": 1450939420000
        },
        {
            "path": "base/js/base.js",
            "id": "base/js/base.js",
            "_requiredCSSMap": {},
            "_requiredModuleMap": {},
            "_requiredAsyncModuleMap": {},
            "_requiredTextToResolvedID": {},
            "type": "JS",
            "networkSize": 0,
            "isModule": true,
            "isNopackage": false,
            "isNonblocking": false,
            "requiredCSS": [
                "../css/base.less"
            ],
            "requiredModules": [
                "jQuery",
                "./mod"
            ],
            "requiredAsyncModules": [],
            "mtime": 1449225484000
        },
        {
            "path": "base/js/jQuery.js",
            "id": "jQuery",
            "_requiredCSSMap": {},
            "_requiredModuleMap": {},
            "_requiredAsyncModuleMap": {},
            "_requiredTextToResolvedID": {},
            "type": "JS",
            "networkSize": 0,
            "isModule": false,
            "isNopackage": false,
            "isNonblocking": false,
            "requiredCSS": [],
            "requiredModules": [],
            "requiredAsyncModules": [],
            "mtime": 1447945500000
        },
        {
            "path": "project/components/back2top/back2top.js",
            "id": "project/components/back2top/back2top.js",
            "_requiredCSSMap": {},
            "_requiredModuleMap": {},
            "_requiredAsyncModuleMap": {},
            "_requiredTextToResolvedID": {},
            "type": "JS",
            "networkSize": 0,
            "isModule": true,
            "isNopackage": false,
            "isNonblocking": false,
            "requiredCSS": [
                "./back2top.css"
            ],
            "requiredModules": [],
            "requiredAsyncModules": [],
            "mtime": 1448620912000
        },
        {
            "path": "project/components/footer/footer.js",
            "id": "project/components/footer/footer.js",
            "_requiredCSSMap": {},
            "_requiredModuleMap": {},
            "_requiredAsyncModuleMap": {},
            "_requiredTextToResolvedID": {},
            "type": "JS",
            "networkSize": 0,
            "isModule": true,
            "isNopackage": false,
            "isNonblocking": false,
            "requiredCSS": [
                "./footer.css"
            ],
            "requiredModules": [],
            "requiredAsyncModules": [],
            "mtime": 1448292656000
        },
        {
            "path": "project/components/header/header.js",
            "id": "header",
            "_requiredCSSMap": {},
            "_requiredModuleMap": {},
            "_requiredAsyncModuleMap": {},
            "_requiredTextToResolvedID": {},
            "type": "JS",
            "networkSize": 0,
            "isModule": true,
            "isNopackage": false,
            "isNonblocking": false,
            "requiredCSS": [
                "./header.css"
            ],
            "requiredModules": [],
            "requiredAsyncModules": [],
            "mtime": 1448292673000
        },
        {
            "path": "project/static/js/app.js",
            "id": "project/static/js/app.js",
            "_requiredCSSMap": {},
            "_requiredModuleMap": {},
            "_requiredAsyncModuleMap": {},
            "_requiredTextToResolvedID": {},
            "type": "JS",
            "networkSize": 0,
            "isModule": true,
            "isNopackage": false,
            "isNonblocking": false,
            "requiredCSS": [
                "../css/app.css"
            ],
            "requiredModules": [
                "header",
                "project/components/footer/footer.js"
            ],
            "requiredAsyncModules": [],
            "mtime": 1448623019000
        }
    ],
    "inferredProjectPaths": null,
    "configurationTrie": null,
    "resourceMap": {
        "JS": {
            "project/null.js": {
                "path": "project/null.js",
                "id": "project/null.js",
                "_requiredCSSMap": {},
                "_requiredModuleMap": {},
                "_requiredAsyncModuleMap": {},
                "_requiredTextToResolvedID": {},
                "type": "JS",
                "networkSize": 0,
                "isModule": false,
                "isNopackage": false,
                "isNonblocking": false,
                "requiredCSS": [],
                "requiredModules": [],
                "requiredAsyncModules": [],
                "mtime": 1450939420000
            },
            "base/js/base.js": {
                "path": "base/js/base.js",
                "id": "base/js/base.js",
                "_requiredCSSMap": {},
                "_requiredModuleMap": {},
                "_requiredAsyncModuleMap": {},
                "_requiredTextToResolvedID": {},
                "type": "JS",
                "networkSize": 0,
                "isModule": true,
                "isNopackage": false,
                "isNonblocking": false,
                "requiredCSS": [
                    "../css/base.less"
                ],
                "requiredModules": [
                    "jQuery",
                    "./mod"
                ],
                "requiredAsyncModules": [],
                "mtime": 1449225484000
            },
            "jQuery": {
                "path": "base/js/jQuery.js",
                "id": "jQuery",
                "_requiredCSSMap": {},
                "_requiredModuleMap": {},
                "_requiredAsyncModuleMap": {},
                "_requiredTextToResolvedID": {},
                "type": "JS",
                "networkSize": 0,
                "isModule": false,
                "isNopackage": false,
                "isNonblocking": false,
                "requiredCSS": [],
                "requiredModules": [],
                "requiredAsyncModules": [],
                "mtime": 1447945500000
            },
            "project/components/back2top/back2top.js": {
                "path": "project/components/back2top/back2top.js",
                "id": "project/components/back2top/back2top.js",
                "_requiredCSSMap": {},
                "_requiredModuleMap": {},
                "_requiredAsyncModuleMap": {},
                "_requiredTextToResolvedID": {},
                "type": "JS",
                "networkSize": 0,
                "isModule": true,
                "isNopackage": false,
                "isNonblocking": false,
                "requiredCSS": [
                    "./back2top.css"
                ],
                "requiredModules": [],
                "requiredAsyncModules": [],
                "mtime": 1448620912000
            },
            "project/components/footer/footer.js": {
                "path": "project/components/footer/footer.js",
                "id": "project/components/footer/footer.js",
                "_requiredCSSMap": {},
                "_requiredModuleMap": {},
                "_requiredAsyncModuleMap": {},
                "_requiredTextToResolvedID": {},
                "type": "JS",
                "networkSize": 0,
                "isModule": true,
                "isNopackage": false,
                "isNonblocking": false,
                "requiredCSS": [
                    "./footer.css"
                ],
                "requiredModules": [],
                "requiredAsyncModules": [],
                "mtime": 1448292656000
            },
            "header": {
                "path": "project/components/header/header.js",
                "id": "header",
                "_requiredCSSMap": {},
                "_requiredModuleMap": {},
                "_requiredAsyncModuleMap": {},
                "_requiredTextToResolvedID": {},
                "type": "JS",
                "networkSize": 0,
                "isModule": true,
                "isNopackage": false,
                "isNonblocking": false,
                "requiredCSS": [
                    "./header.css"
                ],
                "requiredModules": [],
                "requiredAsyncModules": [],
                "mtime": 1448292673000
            },
            "project/static/js/app.js": {
                "path": "project/static/js/app.js",
                "id": "project/static/js/app.js",
                "_requiredCSSMap": {},
                "_requiredModuleMap": {},
                "_requiredAsyncModuleMap": {},
                "_requiredTextToResolvedID": {},
                "type": "JS",
                "networkSize": 0,
                "isModule": true,
                "isNopackage": false,
                "isNonblocking": false,
                "requiredCSS": [
                    "../css/app.css"
                ],
                "requiredModules": [
                    "header",
                    "project/components/footer/footer.js"
                ],
                "requiredAsyncModules": [],
                "mtime": 1448623019000
            }
        }
    },
    "resourcePathMap": {
        "project/null.js": {
            "path": "project/null.js",
            "id": "project/null.js",
            "_requiredCSSMap": {},
            "_requiredModuleMap": {},
            "_requiredAsyncModuleMap": {},
            "_requiredTextToResolvedID": {},
            "type": "JS",
            "networkSize": 0,
            "isModule": false,
            "isNopackage": false,
            "isNonblocking": false,
            "requiredCSS": [],
            "requiredModules": [],
            "requiredAsyncModules": [],
            "mtime": 1450939420000
        },
        "base/js/base.js": {
            "path": "base/js/base.js",
            "id": "base/js/base.js",
            "_requiredCSSMap": {},
            "_requiredModuleMap": {},
            "_requiredAsyncModuleMap": {},
            "_requiredTextToResolvedID": {},
            "type": "JS",
            "networkSize": 0,
            "isModule": true,
            "isNopackage": false,
            "isNonblocking": false,
            "requiredCSS": [
                "../css/base.less"
            ],
            "requiredModules": [
                "jQuery",
                "./mod"
            ],
            "requiredAsyncModules": [],
            "mtime": 1449225484000
        },
        "base/js/jQuery.js": {
            "path": "base/js/jQuery.js",
            "id": "jQuery",
            "_requiredCSSMap": {},
            "_requiredModuleMap": {},
            "_requiredAsyncModuleMap": {},
            "_requiredTextToResolvedID": {},
            "type": "JS",
            "networkSize": 0,
            "isModule": false,
            "isNopackage": false,
            "isNonblocking": false,
            "requiredCSS": [],
            "requiredModules": [],
            "requiredAsyncModules": [],
            "mtime": 1447945500000
        },
        "project/components/back2top/back2top.js": {
            "path": "project/components/back2top/back2top.js",
            "id": "project/components/back2top/back2top.js",
            "_requiredCSSMap": {},
            "_requiredModuleMap": {},
            "_requiredAsyncModuleMap": {},
            "_requiredTextToResolvedID": {},
            "type": "JS",
            "networkSize": 0,
            "isModule": true,
            "isNopackage": false,
            "isNonblocking": false,
            "requiredCSS": [
                "./back2top.css"
            ],
            "requiredModules": [],
            "requiredAsyncModules": [],
            "mtime": 1448620912000
        },
        "project/components/footer/footer.js": {
            "path": "project/components/footer/footer.js",
            "id": "project/components/footer/footer.js",
            "_requiredCSSMap": {},
            "_requiredModuleMap": {},
            "_requiredAsyncModuleMap": {},
            "_requiredTextToResolvedID": {},
            "type": "JS",
            "networkSize": 0,
            "isModule": true,
            "isNopackage": false,
            "isNonblocking": false,
            "requiredCSS": [
                "./footer.css"
            ],
            "requiredModules": [],
            "requiredAsyncModules": [],
            "mtime": 1448292656000
        },
        "project/components/header/header.js": {
            "path": "project/components/header/header.js",
            "id": "header",
            "_requiredCSSMap": {},
            "_requiredModuleMap": {},
            "_requiredAsyncModuleMap": {},
            "_requiredTextToResolvedID": {},
            "type": "JS",
            "networkSize": 0,
            "isModule": true,
            "isNopackage": false,
            "isNonblocking": false,
            "requiredCSS": [
                "./header.css"
            ],
            "requiredModules": [],
            "requiredAsyncModules": [],
            "mtime": 1448292673000
        },
        "project/static/js/app.js": {
            "path": "project/static/js/app.js",
            "id": "project/static/js/app.js",
            "_requiredCSSMap": {},
            "_requiredModuleMap": {},
            "_requiredAsyncModuleMap": {},
            "_requiredTextToResolvedID": {},
            "type": "JS",
            "networkSize": 0,
            "isModule": true,
            "isNopackage": false,
            "isNonblocking": false,
            "requiredCSS": [
                "../css/app.css"
            ],
            "requiredModules": [
                "header",
                "project/components/footer/footer.js"
            ],
            "requiredAsyncModules": [],
            "mtime": 1448623019000
        }
    },
    "typeToMap": {}
}